shapely/linear.py
shapely/conftest.py
shapely/_geometry_helpers.cpython-313t-aarch64-linux-gnu.so
shapely/set_operations.py
shapely/predicates.py
shapely/lib.cpython-313t-aarch64-linux-gnu.so
shapely/creation.py
shapely/__init__.py
shapely/wkt.py
shapely/testing.py
shapely/errors.py
shapely/wkb.py
shapely/geos.py
shapely/speedups.py
shapely/ops.py
shapely/_pygeos_api.pxd
shapely/coordinates.py
shapely/decorators.py
shapely/plotting.py
shapely/io.py
shapely/validation.py
shapely/_geos.cpython-313t-aarch64-linux-gnu.so
shapely/strtree.py
shapely/_geos.pxd
shapely/_enum.py
shapely/measurement.py
shapely/affinity.py
shapely/_geometry.py
shapely/coords.py
shapely/constructive.py
shapely/_coverage.py
shapely/prepared.py
shapely/_ragged_array.py
shapely/_version.py
shapely/vectorized/__init__.py
shapely/algorithms/_oriented_envelope.py
shapely/algorithms/__init__.py
shapely/algorithms/cga.py
shapely/algorithms/polylabel.py
shapely/tests/test_linear.py
shapely/tests/test_geometry.py
shapely/tests/common.py
shapely/tests/test_constructive.py
shapely/tests/__init__.py
shapely/tests/test_set_operations.py
shapely/tests/test_measurement.py
shapely/tests/test_creation_indices.py
shapely/tests/test_testing.py
shapely/tests/test_plotting.py
shapely/tests/test_misc.py
shapely/tests/test_predicates.py
shapely/tests/test_strtree.py
shapely/tests/test_coordinates.py
shapely/tests/test_decorators.py
shapely/tests/test_io.py
shapely/tests/test_creation.py
shapely/tests/test_coverage.py
shapely/tests/test_ragged_array.py
shapely/tests/geometry/test_geometry_base.py
shapely/tests/geometry/__init__.py
shapely/tests/geometry/test_point.py
shapely/tests/geometry/test_format.py
shapely/tests/geometry/test_multipoint.py
shapely/tests/geometry/test_collection.py
shapely/tests/geometry/test_decimal.py
shapely/tests/geometry/test_multilinestring.py
shapely/tests/geometry/test_linestring.py
shapely/tests/geometry/test_polygon.py
shapely-2.1.1.dist-info/RECORD
shapely-2.1.1.dist-info/WHEEL
shapely-2.1.1.dist-info/METADATA
shapely-2.1.1.dist-info/top_level.txt
shapely-2.1.1.dist-info/licenses/LICENSE.txt
shapely-2.1.1.dist-info/licenses/LICENSE_GEOS
