Metadata-Version: 2.4
Name: shapely
Version: 2.1.1
Summary: Manipulation and analysis of geometric objects
Author: Sean Gillies
Maintainer: Shapely contributors
License: BSD 3-Clause
Project-URL: Documentation, https://shapely.readthedocs.io/
Project-URL: Repository, https://github.com/shapely/shapely
Keywords: geometry,topology,gis
Classifier: Development Status :: 5 - Production/Stable
Classifier: Intended Audience :: Developers
Classifier: Intended Audience :: Science/Research
Classifier: License :: OSI Approved :: BSD License
Classifier: Operating System :: Unix
Classifier: Operating System :: MacOS
Classifier: Operating System :: Microsoft :: Windows
Classifier: Programming Language :: Python :: 3
Classifier: Programming Language :: Python :: 3.10
Classifier: Programming Language :: Python :: 3.11
Classifier: Programming Language :: Python :: 3.12
Classifier: Programming Language :: Python :: 3.13
Classifier: Topic :: Scientific/Engineering :: GIS
Requires-Python: >=3.10
License-File: LICENSE.txt
Requires-Dist: numpy>=1.21
Provides-Extra: test
Requires-Dist: pytest; extra == "test"
Requires-Dist: pytest-cov; extra == "test"
Requires-Dist: scipy-doctest; extra == "test"
Provides-Extra: docs
Requires-Dist: numpydoc==1.1.*; extra == "docs"
Requires-Dist: matplotlib; extra == "docs"
Requires-Dist: sphinx; extra == "docs"
Requires-Dist: sphinx-book-theme; extra == "docs"
Requires-Dist: sphinx-remove-toctrees; extra == "docs"
Dynamic: license-file
